dash_json_grid/DashJsonGrid.py
dash_json_grid/__init__.py
dash_json_grid/_imports_.py
dash_json_grid/async-DashJsonGrid.js
dash_json_grid/async-DashJsonGrid.js.map
dash_json_grid/dash_json_grid.min.js
dash_json_grid/dash_json_grid.min.js.map
dash_json_grid/metadata.json
dash_json_grid/mixins.py
dash_json_grid/package-info.json
dash_json_grid/typehints.py
dash_json_grid-0.5.0.dist-info/LICENSE
dash_json_grid-0.5.0.dist-info/METADATA
dash_json_grid-0.5.0.dist-info/WHEEL
dash_json_grid-0.5.0.dist-info/top_level.txt
dash_json_grid-0.5.0.dist-info/RECORD
